{
    "size": 23,
    "num_dockers": 13,
    "discos": [],
    "num_files": 14,
    "avg_size_service": 1.7692307692307692,
    "buses": [],
    "num_gates": 0,
    "langs": [
        "java",
        "dockerfile"
    ],
    "num_discos": 0,
    "num_monitors": 0,
    "dockers": [
        {
            "monitors": [],
            "cmd": "java -agentlib:TakipiAgent -jar scala-boom.jar",
            "discos": [],
            "servers": [],
            "cmd_keywords": [
                "jar",
                "boom",
                "agentlib",
                "scala",
                "java"
            ],
            "from": "alpine",
            "path": "/alpine/3.3/Dockerfile",
            "keywords": [
                "opt",
                "jdk",
                "lib",
                "jre",
                "usr"
            ],
            "buses": [],
            "langs": [
                "java"
            ],
            "gates": [],
            "dbs": [
                "sqlite"
            ],
            "from_full": "alpine:3.3"
        },
        {
            "monitors": [],
            "cmd": "java -agentlib:TakipiAgent -jar scala-boom.jar",
            "discos": [],
            "servers": [],
            "cmd_keywords": [
                "jar",
                "boom",
                "agentlib",
                "scala",
                "java"
            ],
            "from": "alpine",
            "path": "/alpine/3.4/Dockerfile",
            "keywords": [
                "opt",
                "jdk",
                "lib",
                "glibc",
                "jre"
            ],
            "buses": [],
            "langs": [
                "java"
            ],
            "gates": [],
            "dbs": [
                "sqlite"
            ],
            "from_full": "alpine:3.4"
        },
        {
            "monitors": [],
            "cmd": "java -agentlib:TakipiAgent -jar scala-boom.jar",
            "discos": [],
            "servers": [],
            "cmd_keywords": [
                "jar",
                "boom",
                "agentlib",
                "scala",
                "java"
            ],
            "from": "alpine",
            "path": "/alpine/3.2/Dockerfile",
            "keywords": [
                "opt",
                "jdk",
                "lib",
                "jre",
                "usr"
            ],
            "buses": [],
            "langs": [
                "java"
            ],
            "gates": [],
            "dbs": [
                "sqlite"
            ],
            "from_full": "alpine:3.2"
        },
        {
            "monitors": [],
            "cmd": "java -agentlib:TakipiAgent -jar scala-boom.jar",
            "discos": [],
            "servers": [],
            "cmd_keywords": [
                "jar",
                "boom",
                "agentlib",
                "scala",
                "java"
            ],
            "from": "openjdk",
            "path": "/alpine/openjdk-8-jre-alpine/Dockerfile",
            "keywords": [
                "opt",
                "jdk",
                "jre",
                "lib",
                "tmp"
            ],
            "buses": [],
            "langs": [
                "java"
            ],
            "gates": [],
            "dbs": [
                "oracle"
            ],
            "from_full": "openjdk:8-jre-alpine"
        },
        {
            "monitors": [],
            "cmd": "java -agentpath:takipi/lib/libTakipiAgent.so -jar scala-boom.jar",
            "discos": [],
            "servers": [],
            "cmd_keywords": [
                "jar",
                "lib",
                "boom",
                "scala",
                "takipi"
            ],
            "from": "frolvlad/alpine-glibc",
            "path": "/alpine/docker-alpine-oraclejre8/Dockerfile",
            "keywords": [
                "java",
                "home",
                "jre",
                "lib",
                "bin"
            ],
            "buses": [],
            "langs": [
                "java"
            ],
            "gates": [],
            "dbs": [
                "oracle"
            ],
            "from_full": "frolvlad/alpine-glibc:alpine-3.8"
        },
        {
            "monitors": [],
            "cmd": "",
            "discos": [],
            "servers": [],
            "cmd_keywords": [],
            "from": "",
            "path": "/ubuntu/t4c/Dockerfile",
            "keywords": [],
            "buses": [],
            "langs": [],
            "gates": [],
            "dbs": []
        },
        {
            "monitors": [],
            "cmd": "java -agentlib:TakipiAgent -jar scala-boom.jar",
            "discos": [],
            "servers": [],
            "cmd_keywords": [
                "jar",
                "boom",
                "agentlib",
                "scala",
                "java"
            ],
            "from": "ubuntu",
            "path": "/ubuntu/12.04/Dockerfile",
            "keywords": [
                "wget",
                "get",
                "com",
                "takipi",
                "apt"
            ],
            "buses": [],
            "langs": [
                "java"
            ],
            "gates": [],
            "dbs": [],
            "from_full": "ubuntu:12.04"
        },
        {
            "monitors": [],
            "cmd": "java -agentlib:TakipiAgent -jar scala-boom.jar",
            "discos": [],
            "servers": [],
            "cmd_keywords": [
                "jar",
                "boom",
                "agentlib",
                "scala",
                "java"
            ],
            "from": "ubuntu",
            "path": "/ubuntu/15.10/Dockerfile",
            "keywords": [
                "takipi",
                "wget",
                "get",
                "com",
                "apt"
            ],
            "buses": [],
            "langs": [
                "java"
            ],
            "gates": [],
            "dbs": [],
            "from_full": "ubuntu:15.10"
        },
        {
            "cmd_keywords": [],
            "cmd": "",
            "from": "",
            "path": "/centos/t4c/Dockerfile"
        },
        {
            "monitors": [],
            "cmd": "java -agentlib:TakipiAgent -jar scala-boom.jar",
            "discos": [],
            "servers": [],
            "cmd_keywords": [
                "jar",
                "boom",
                "agentlib",
                "scala",
                "java"
            ],
            "from": "centos",
            "path": "/centos/7/Dockerfile",
            "keywords": [
                "com",
                "takipi",
                "scala",
                "dev",
                "boom"
            ],
            "buses": [],
            "langs": [
                "java"
            ],
            "gates": [],
            "dbs": [],
            "from_full": "centos:7"
        },
        {
            "monitors": [],
            "cmd": "/opt/takipi/bin/takipi-service --noforkdaemon",
            "discos": [],
            "servers": [],
            "cmd_keywords": [
                "takipi",
                "service",
                "opt",
                "noforkdaemon",
                "bin"
            ],
            "from": "java",
            "path": "/rdp/Dockerfile",
            "keywords": [
                "machine",
                "port",
                "name",
                "dev",
                "listen"
            ],
            "buses": [],
            "langs": [
                "java"
            ],
            "gates": [],
            "dbs": [],
            "from_full": "java:8"
        },
        {
            "monitors": [],
            "cmd": "java -agentlib:TakipiAgent -jar scala-boom.jar",
            "discos": [],
            "servers": [],
            "cmd_keywords": [
                "jar",
                "boom",
                "agentlib",
                "scala",
                "java"
            ],
            "from": "java",
            "path": "/elasticbeanstalk/ubuntu/Dockerfile",
            "keywords": [
                "takipi",
                "com",
                "wget",
                "dev",
                "scala"
            ],
            "buses": [],
            "langs": [
                "java"
            ],
            "gates": [],
            "dbs": [],
            "from_full": "java:7"
        },
        {
            "monitors": [],
            "cmd": "java -agentlib:TakipiAgent -jar scala-boom.jar",
            "discos": [],
            "servers": [],
            "cmd_keywords": [
                "jar",
                "boom",
                "agentlib",
                "scala",
                "java"
            ],
            "from": "tcnksm/centos-java",
            "path": "/elasticbeanstalk/centos/Dockerfile",
            "keywords": [
                "takipi",
                "com",
                "dev",
                "scala",
                "boom"
            ],
            "buses": [],
            "langs": [
                "java"
            ],
            "gates": [],
            "dbs": [],
            "from_full": "tcnksm/centos-java"
        }
    ],
    "num_dbs": 2,
    "monitors": [],
    "shared_dbs": false,
    "structure": {
        "services": [],
        "detected_dbs": {
            "num": 0,
            "names": [],
            "services": [],
            "shared_dbs": false
        },
        "num_services": 0,
        "path": []
    },
    "num_buses": 0,
    "servers": [],
    "url": "git://github.com/chook/docker-takipi.git",
    "num_services": 0,
    "gates": [],
    "files": [],
    "name": "chook/docker-takipi",
    "languages": [
        "dockerfile"
    ],
    "images": [
        "centos",
        "frolvlad/alpine-glibc",
        "tcnksm/centos-java",
        "ubuntu",
        "openjdk",
        "java",
        "alpine"
    ],
    "dbs": [
        "sqlite",
        "oracle"
    ],
    "num_servers": 0,
    "num_langs": 2
}