{
    "size": 118,
    "num_dockers": 3,
    "discos": [],
    "num_files": 8,
    "avg_size_service": 39.333333333333336,
    "buses": [],
    "num_gates": 0,
    "langs": [
        "html",
        "javascript"
    ],
    "num_discos": 0,
    "num_monitors": 0,
    "dockers": [
        {
            "monitors": [],
            "cmd": "npm start",
            "discos": [],
            "servers": [
                "node"
            ],
            "cmd_keywords": [
                "start",
                "npm"
            ],
            "from": "node",
            "path": "/services/messages/Dockerfile",
            "keywords": [
                "install",
                "npm"
            ],
            "buses": [],
            "langs": [],
            "gates": [],
            "dbs": [],
            "from_full": "node:latest"
        },
        {
            "monitors": [],
            "cmd": "npm start",
            "discos": [],
            "servers": [
                "node"
            ],
            "cmd_keywords": [
                "start",
                "npm"
            ],
            "from": "node",
            "path": "/services/auth/Dockerfile",
            "keywords": [
                "install",
                "npm"
            ],
            "buses": [],
            "langs": [],
            "gates": [],
            "dbs": [],
            "from_full": "node:latest"
        },
        {
            "monitors": [],
            "cmd": "npm start",
            "discos": [],
            "servers": [
                "node"
            ],
            "cmd_keywords": [
                "start",
                "npm"
            ],
            "from": "node",
            "path": "/services/web/Dockerfile",
            "keywords": [
                "install",
                "npm"
            ],
            "buses": [],
            "langs": [],
            "gates": [],
            "dbs": [],
            "from_full": "node:latest"
        }
    ],
    "num_dbs": 0,
    "monitors": [],
    "shared_dbs": false,
    "structure": {
        "services": [],
        "detected_dbs": {
            "num": 0,
            "names": [],
            "services": [],
            "shared_dbs": false
        },
        "num_services": 0,
        "path": []
    },
    "num_buses": 0,
    "servers": [
        "mongoose",
        "node",
        "express"
    ],
    "url": "git://github.com/denis-onder/docker-microservices.git",
    "num_services": 0,
    "gates": [],
    "files": [
        {
            "monitors": [],
            "buses": [],
            "discos": [],
            "gates": [],
            "dbs": [],
            "servers": [],
            "path": "/package.json"
        },
        {
            "monitors": [],
            "buses": [],
            "discos": [],
            "gates": [],
            "dbs": [],
            "servers": [
                "mongoose",
                "express",
                "node"
            ],
            "path": "/services/messages/package.json"
        },
        {
            "monitors": [],
            "buses": [],
            "discos": [],
            "gates": [],
            "dbs": [],
            "servers": [
                "mongoose",
                "express",
                "node"
            ],
            "path": "/services/auth/package.json"
        },
        {
            "monitors": [],
            "buses": [],
            "discos": [],
            "gates": [],
            "dbs": [],
            "servers": [
                "express",
                "node"
            ],
            "path": "/services/web/package.json"
        }
    ],
    "name": "denis-onder/docker-microservices",
    "languages": [
        "javascript",
        "html"
    ],
    "images": [
        "node"
    ],
    "dbs": [],
    "num_servers": 3,
    "num_langs": 2
}