{
    "name": "matevip/matecloud",
    "num_dbs": 3,
    "num_services": 0,
    "num_files": 40,
    "servers": [
        "tomcat",
        "spring",
        "jetty"
    ],
    "url": "git://github.com/matevip/matecloud.git",
    "discos": [],
    "structure": {
        "path": [],
        "services": [],
        "detected_dbs": {
            "shared_dbs": false,
            "services": [],
            "num": 0,
            "names": []
        },
        "num_services": 0
    },
    "num_buses": 1,
    "size": 764,
    "dockers": [],
    "languages": [
        "java"
    ],
    "dbs": [
        "velocity",
        "redis",
        "mysql"
    ],
    "monitors": [],
    "shared_dbs": false,
    "avg_size_service": 764.0,
    "num_monitors": 0,
    "files": [
        {
            "path": "/pom.xml"
        },
        {
            "path": "/mate-uaa/pom.xml"
        },
        {
            "monitors": [],
            "servers": [],
            "path": "/mate-support/pom.xml",
            "discos": [],
            "dbs": [],
            "gates": [],
            "buses": []
        },
        {
            "monitors": [],
            "servers": [
                "tomcat",
                "spring",
                "jetty"
            ],
            "path": "/mate-support/mate-admin/pom.xml",
            "discos": [],
            "dbs": [],
            "gates": [],
            "buses": []
        },
        {
            "monitors": [],
            "servers": [
                "spring"
            ],
            "path": "/mate-support/mate-code/pom.xml",
            "discos": [],
            "dbs": [
                "velocity",
                "mysql"
            ],
            "gates": [],
            "buses": []
        },
        {
            "path": "/mate-support/mate-job/pom.xml"
        },
        {
            "monitors": [],
            "servers": [],
            "path": "/mate-platform/pom.xml",
            "discos": [],
            "dbs": [],
            "gates": [],
            "buses": []
        },
        {
            "monitors": [],
            "servers": [
                "spring"
            ],
            "path": "/mate-platform/mate-system-api/pom.xml",
            "discos": [],
            "dbs": [],
            "gates": [],
            "buses": []
        },
        {
            "path": "/mate-platform/mate-system/pom.xml"
        },
        {
            "monitors": [],
            "servers": [
                "spring"
            ],
            "path": "/mate-platform/mate-component-api/pom.xml",
            "discos": [],
            "dbs": [],
            "gates": [],
            "buses": []
        },
        {
            "monitors": [],
            "servers": [
                "spring"
            ],
            "path": "/mate-platform/mate-component/pom.xml",
            "discos": [],
            "dbs": [
                "redis"
            ],
            "gates": [],
            "buses": []
        },
        {
            "path": "/mate-core/pom.xml"
        },
        {
            "monitors": [],
            "servers": [
                "spring"
            ],
            "path": "/mate-core/mate-starter-elasticsearch/pom.xml",
            "discos": [],
            "dbs": [],
            "gates": [],
            "buses": []
        },
        {
            "monitors": [],
            "servers": [
                "spring"
            ],
            "path": "/mate-core/mate-starter-log/pom.xml",
            "discos": [],
            "dbs": [],
            "gates": [],
            "buses": []
        },
        {
            "monitors": [],
            "servers": [
                "spring"
            ],
            "path": "/mate-core/mate-starter-rocketmq/pom.xml",
            "discos": [],
            "dbs": [],
            "gates": [],
            "buses": []
        },
        {
            "path": "/mate-core/mate-starter-security/pom.xml"
        },
        {
            "monitors": [],
            "servers": [
                "spring"
            ],
            "path": "/mate-core/mate-starter-redis/pom.xml",
            "discos": [],
            "dbs": [
                "redis"
            ],
            "gates": [],
            "buses": []
        },
        {
            "monitors": [],
            "servers": [
                "spring"
            ],
            "path": "/mate-core/mate-starter-common/pom.xml",
            "discos": [],
            "dbs": [],
            "gates": [],
            "buses": []
        },
        {
            "monitors": [],
            "servers": [
                "spring"
            ],
            "path": "/mate-core/mate-starter-kafka/pom.xml",
            "discos": [],
            "dbs": [],
            "gates": [],
            "buses": [
                "kafka"
            ]
        },
        {
            "monitors": [],
            "servers": [
                "spring"
            ],
            "path": "/mate-core/mate-starter-dubbo/pom.xml",
            "discos": [],
            "dbs": [],
            "gates": [],
            "buses": []
        },
        {
            "monitors": [],
            "servers": [],
            "path": "/mate-core/mate-starter-file/pom.xml",
            "discos": [],
            "dbs": [],
            "gates": [],
            "buses": []
        },
        {
            "monitors": [],
            "servers": [
                "spring"
            ],
            "path": "/mate-core/mate-starter-feign/pom.xml",
            "discos": [],
            "dbs": [],
            "gates": [],
            "buses": []
        },
        {
            "path": "/mate-core/mate-starter-dependencies/pom.xml"
        },
        {
            "monitors": [],
            "servers": [
                "spring"
            ],
            "path": "/mate-core/mate-starter-gray/pom.xml",
            "discos": [],
            "dbs": [],
            "gates": [],
            "buses": []
        },
        {
            "monitors": [],
            "servers": [],
            "path": "/mate-core/mate-starter-jetcache/pom.xml",
            "discos": [],
            "dbs": [
                "redis"
            ],
            "gates": [],
            "buses": []
        },
        {
            "monitors": [],
            "servers": [],
            "path": "/mate-core/mate-starter-auth/pom.xml",
            "discos": [],
            "dbs": [],
            "gates": [],
            "buses": []
        },
        {
            "monitors": [],
            "servers": [
                "spring"
            ],
            "path": "/mate-core/mate-starter-sms/pom.xml",
            "discos": [],
            "dbs": [
                "redis"
            ],
            "gates": [],
            "buses": []
        },
        {
            "monitors": [],
            "servers": [
                "spring"
            ],
            "path": "/mate-core/mate-starter-cloud/pom.xml",
            "discos": [],
            "dbs": [],
            "gates": [
                "gateway"
            ],
            "buses": []
        },
        {
            "monitors": [],
            "servers": [
                "spring"
            ],
            "path": "/mate-core/mate-starter-sharding/pom.xml",
            "discos": [],
            "dbs": [
                "mysql"
            ],
            "gates": [],
            "buses": []
        },
        {
            "monitors": [],
            "servers": [
                "spring"
            ],
            "path": "/mate-core/mate-starter-oss/pom.xml",
            "discos": [],
            "dbs": [
                "redis"
            ],
            "gates": [],
            "buses": []
        },
        {
            "path": "/mate-core/mate-starter-web/pom.xml"
        },
        {
            "monitors": [],
            "servers": [
                "spring"
            ],
            "path": "/mate-core/mate-starter-database/pom.xml",
            "discos": [],
            "dbs": [
                "mysql"
            ],
            "gates": [],
            "buses": []
        },
        {
            "path": "/mate-mq/pom.xml"
        },
        {
            "monitors": [],
            "servers": [],
            "path": "/mate-mq/mate-message-consumer/pom.xml",
            "discos": [],
            "dbs": [],
            "gates": [],
            "buses": []
        },
        {
            "monitors": [],
            "servers": [],
            "path": "/mate-mq/mate-log-api/pom.xml",
            "discos": [],
            "dbs": [],
            "gates": [],
            "buses": []
        },
        {
            "monitors": [],
            "servers": [],
            "path": "/mate-mq/mate-log-consumer/pom.xml",
            "discos": [],
            "dbs": [],
            "gates": [],
            "buses": []
        },
        {
            "path": "/mate-mq/mate-log-producer/pom.xml"
        },
        {
            "monitors": [],
            "servers": [],
            "path": "/mate-mq/mate-message-producer/pom.xml",
            "discos": [],
            "dbs": [],
            "gates": [],
            "buses": []
        },
        {
            "path": "/mate-gateway/pom.xml"
        }
    ],
    "langs": [
        "java"
    ],
    "num_servers": 3,
    "buses": [
        "kafka"
    ],
    "num_langs": 1,
    "num_gates": 1,
    "num_discos": 0,
    "images": [],
    "num_dockers": 0,
    "gates": [
        "gateway"
    ]
}