{
    "avg_size_service": 493.0,
    "discos": [
        "eureka"
    ],
    "images": [],
    "num_dockers": 0,
    "num_servers": 1,
    "langs": [
        "java"
    ],
    "languages": [
        "java"
    ],
    "num_services": 0,
    "num_gates": 1,
    "num_langs": 1,
    "monitors": [
        "monitoring"
    ],
    "gates": [
        "gateway"
    ],
    "servers": [
        "spring"
    ],
    "num_monitors": 1,
    "structure": {
        "path": [],
        "services": [],
        "num_services": 0,
        "detected_dbs": {
            "names": [],
            "num": 0,
            "services": [],
            "shared_dbs": false
        }
    },
    "size": 493,
    "url": "git://github.com/usj94/springboot-microservices-docker.git",
    "num_buses": 0,
    "shared_dbs": false,
    "files": [
        {
            "path": "/statistics-service/pom.xml",
            "discos": [],
            "monitors": [],
            "gates": [],
            "servers": [
                "spring"
            ],
            "dbs": [],
            "buses": []
        },
        {
            "path": "/config/pom.xml",
            "discos": [],
            "monitors": [],
            "gates": [],
            "servers": [
                "spring"
            ],
            "dbs": [],
            "buses": []
        },
        {
            "path": "/monitoring/pom.xml",
            "discos": [],
            "monitors": [
                "monitoring"
            ],
            "gates": [],
            "servers": [
                "spring"
            ],
            "dbs": [],
            "buses": []
        },
        {
            "path": "/gateway/pom.xml",
            "discos": [],
            "monitors": [],
            "gates": [
                "gateway"
            ],
            "servers": [
                "spring"
            ],
            "dbs": [],
            "buses": []
        },
        {
            "path": "/notification-service/pom.xml",
            "discos": [],
            "monitors": [],
            "gates": [],
            "servers": [
                "spring"
            ],
            "dbs": [],
            "buses": []
        },
        {
            "path": "/registry/pom.xml",
            "discos": [
                "eureka"
            ],
            "monitors": [],
            "gates": [],
            "servers": [
                "spring"
            ],
            "dbs": [],
            "buses": []
        },
        {
            "path": "/mongodb/pom.xml",
            "discos": [],
            "monitors": [],
            "gates": [],
            "servers": [
                "spring"
            ],
            "dbs": [
                "mongodb"
            ],
            "buses": []
        },
        {
            "path": "/account-service/pom.xml",
            "discos": [],
            "monitors": [],
            "gates": [],
            "servers": [
                "spring"
            ],
            "dbs": [],
            "buses": []
        }
    ],
    "num_discos": 1,
    "dockers": [],
    "name": "usj94/springboot-microservices-docker",
    "buses": [],
    "num_files": 9,
    "dbs": [
        "db"
    ],
    "num_dbs": 1
}