{
    "gates": [],
    "images": [
        "openjdk"
    ],
    "num_dbs": 0,
    "structure": {
        "num_services": 0,
        "path": [],
        "services": [],
        "detected_dbs": {
            "num": 0,
            "services": [],
            "shared_dbs": false,
            "names": []
        }
    },
    "num_files": 3,
    "num_gates": 0,
    "discos": [],
    "num_dockers": 1,
    "shared_dbs": false,
    "languages": [
        "java",
        "shell",
        "dockerfile"
    ],
    "name": "Abhi904485/simple-rest-apis-microservice-docker",
    "num_langs": 3,
    "avg_size_service": 8.0,
    "monitors": [],
    "num_servers": 1,
    "num_services": 0,
    "dbs": [],
    "langs": [
        "java",
        "shell",
        "dockerfile"
    ],
    "dockers": [
        {
            "gates": [],
            "path": "/Dockerfile",
            "langs": [],
            "dbs": [],
            "buses": [],
            "servers": [
                "spring"
            ],
            "from": "openjdk",
            "discos": [],
            "from_full": "openjdk:8-jdk-slim",
            "cmd": "mvn spring-boot:run",
            "monitors": [],
            "cmd_keywords": [
                "spring",
                "mvn",
                "boot",
                "run"
            ],
            "keywords": [
                "maven",
                "tar",
                "apt",
                "apache",
                "get"
            ]
        }
    ],
    "buses": [],
    "servers": [
        "spring"
    ],
    "size": 8,
    "files": [
        {
            "gates": [],
            "path": "/pom.xml",
            "discos": [],
            "dbs": [],
            "buses": [],
            "servers": [
                "spring"
            ],
            "monitors": []
        }
    ],
    "num_buses": 0,
    "num_monitors": 0,
    "url": "git://github.com/Abhi904485/simple-rest-apis-microservice-docker.git",
    "num_discos": 0
}