{
    "monitors": [],
    "structure": {
        "path": [],
        "detected_dbs": {
            "shared_dbs": false,
            "services": [],
            "names": [],
            "num": 0
        },
        "services": [],
        "num_services": 0
    },
    "num_langs": 2,
    "name": "leo-coutinho/Sample-Spring-Microservices",
    "num_dockers": 4,
    "buses": [],
    "dbs": [],
    "size": 200,
    "num_discos": 1,
    "shared_dbs": false,
    "discos": [
        "eureka"
    ],
    "images": [
        "openjdk"
    ],
    "num_servers": 1,
    "files": [
        {
            "gates": [
                "gateway"
            ],
            "buses": [],
            "monitors": [],
            "servers": [
                "spring"
            ],
            "path": "/pom.xml",
            "discos": [
                "eureka"
            ],
            "dbs": []
        },
        {
            "gates": [],
            "buses": [],
            "monitors": [],
            "servers": [
                "spring"
            ],
            "path": "/zipkin-service/pom.xml",
            "discos": [],
            "dbs": []
        },
        {
            "gates": [
                "gateway",
                "zuul"
            ],
            "buses": [],
            "monitors": [],
            "servers": [
                "spring"
            ],
            "path": "/gateway-service/pom.xml",
            "discos": [
                "eureka"
            ],
            "dbs": []
        },
        {
            "gates": [],
            "buses": [],
            "monitors": [],
            "servers": [
                "spring"
            ],
            "path": "/customer-service/pom.xml",
            "discos": [
                "eureka"
            ],
            "dbs": []
        },
        {
            "gates": [],
            "buses": [],
            "monitors": [],
            "servers": [
                "spring"
            ],
            "path": "/discovery-service/pom.xml",
            "discos": [
                "eureka"
            ],
            "dbs": []
        },
        {
            "gates": [],
            "buses": [],
            "monitors": [],
            "servers": [
                "spring"
            ],
            "path": "/account-service/pom.xml",
            "discos": [
                "eureka"
            ],
            "dbs": []
        }
    ],
    "dockers": [
        {
            "buses": [],
            "cmd_keywords": [],
            "gates": [],
            "monitors": [],
            "dbs": [],
            "from": "openjdk",
            "path": "/gateway-service/Dockerfile",
            "from_full": "openjdk",
            "cmd": "",
            "keywords": [],
            "discos": [],
            "servers": [],
            "langs": []
        },
        {
            "buses": [],
            "cmd_keywords": [],
            "gates": [],
            "monitors": [],
            "dbs": [],
            "from": "openjdk",
            "path": "/customer-service/Dockerfile",
            "from_full": "openjdk",
            "cmd": "",
            "keywords": [],
            "discos": [],
            "servers": [],
            "langs": []
        },
        {
            "buses": [],
            "cmd_keywords": [],
            "gates": [],
            "monitors": [],
            "dbs": [],
            "from": "openjdk",
            "path": "/discovery-service/Dockerfile",
            "from_full": "openjdk",
            "cmd": "",
            "keywords": [],
            "discos": [],
            "servers": [],
            "langs": []
        },
        {
            "buses": [],
            "cmd_keywords": [],
            "gates": [],
            "monitors": [],
            "dbs": [],
            "from": "openjdk",
            "path": "/account-service/Dockerfile",
            "from_full": "openjdk",
            "cmd": "",
            "keywords": [],
            "discos": [],
            "servers": [],
            "langs": []
        }
    ],
    "url": "git://github.com/leo-coutinho/Sample-Spring-Microservices.git",
    "gates": [
        "zuul"
    ],
    "num_files": 11,
    "num_services": 0,
    "num_gates": 1,
    "num_dbs": 0,
    "avg_size_service": 50.0,
    "langs": [
        "groovy",
        "java"
    ],
    "num_buses": 0,
    "languages": [
        "java",
        "groovy"
    ],
    "num_monitors": 0,
    "servers": [
        "spring"
    ]
}