{
    "discos": [],
    "avg_size_service": 964.0,
    "buses": [],
    "num_gates": 0,
    "name": "SarankumarChandrasekan/DockerPromethContainerMonitor",
    "structure": {
        "path": "/docker-compose.yml",
        "services": [
            {
                "name": "pushgateway",
                "dbs": [],
                "depends_on": [],
                "discos": [],
                "image_full": "prom/pushgateway",
                "image": "prom/pushgateway",
                "servers": [],
                "buses": [],
                "monitors": [],
                "gates": []
            },
            {
                "name": "alertmanager",
                "dbs": [],
                "depends_on": [],
                "discos": [],
                "image_full": "prom/alertmanager:v0.15.2",
                "image": "prom/alertmanager",
                "servers": [],
                "buses": [],
                "monitors": [],
                "gates": []
            },
            {
                "name": "caddy",
                "dbs": [],
                "depends_on": [],
                "discos": [],
                "image_full": "stefanprodan/caddy",
                "image": "stefanprodan/caddy",
                "servers": [
                    "caddy"
                ],
                "buses": [],
                "monitors": [],
                "gates": []
            },
            {
                "name": "nodeexporter",
                "dbs": [],
                "depends_on": [],
                "discos": [],
                "image_full": "prom/node-exporter:v0.16.0",
                "image": "prom/node-exporter",
                "servers": [
                    "node"
                ],
                "buses": [],
                "monitors": [],
                "gates": []
            },
            {
                "name": "grafana",
                "dbs": [],
                "depends_on": [],
                "discos": [],
                "image_full": "grafana/grafana:5.2.4",
                "image": "grafana/grafana",
                "servers": [],
                "buses": [],
                "monitors": [
                    "grafana"
                ],
                "gates": []
            },
            {
                "name": "cadvisor",
                "dbs": [],
                "depends_on": [],
                "discos": [],
                "image_full": "google/cadvisor:v0.28.3",
                "image": "google/cadvisor",
                "servers": [],
                "buses": [],
                "monitors": [],
                "gates": []
            },
            {
                "name": "prometheus",
                "dbs": [],
                "depends_on": [],
                "discos": [],
                "image_full": "prom/prometheus:v2.4.2",
                "image": "prom/prometheus",
                "servers": [],
                "buses": [],
                "monitors": [
                    "prometheus"
                ],
                "gates": []
            }
        ],
        "detected_dbs": {
            "names": [],
            "num": 0,
            "shared_dbs": false,
            "services": []
        },
        "num_services": 7
    },
    "dbs": [],
    "dockers": [],
    "gates": [],
    "size": 964,
    "num_monitors": 2,
    "images": [],
    "num_buses": 0,
    "num_services": 7,
    "servers": [
        "node",
        "caddy"
    ],
    "shared_dbs": false,
    "monitors": [
        "prometheus",
        "grafana"
    ],
    "num_discos": 0,
    "languages": [
        "shell"
    ],
    "url": "git://github.com/SarankumarChandrasekan/DockerPromethContainerMonitor.git",
    "langs": [
        "shell"
    ],
    "num_dbs": 0,
    "num_servers": 2,
    "num_langs": 1,
    "files": [],
    "num_dockers": 0,
    "num_files": 1
}