{
    "buses": [
        "rabbitmq"
    ],
    "num_langs": 1,
    "dbs": [],
    "languages": [
        "c#"
    ],
    "files": [],
    "size": 4199,
    "name": "Todai88/CoreTesting",
    "num_servers": 0,
    "structure": {
        "num_services": 2,
        "services": [
            {
                "image": "testcore",
                "servers": [],
                "name": "main-web",
                "monitors": [],
                "dbs": [],
                "image_full": "testcore",
                "buses": [],
                "discos": [],
                "depends_on": [],
                "gates": []
            },
            {
                "image": "rabbitmq",
                "servers": [],
                "name": "rabbitmq",
                "monitors": [],
                "dbs": [],
                "image_full": "rabbitmq:3.6-management",
                "buses": [
                    "rabbitmq"
                ],
                "discos": [],
                "depends_on": [],
                "gates": []
            }
        ],
        "path": "/docker-compose.yml",
        "detected_dbs": {
            "names": [],
            "num": 0,
            "services": [],
            "shared_dbs": false
        }
    },
    "shared_dbs": false,
    "num_services": 2,
    "num_dbs": 0,
    "discos": [],
    "gates": [],
    "servers": [],
    "images": [],
    "num_gates": 0,
    "num_buses": 1,
    "dockers": [],
    "num_discos": 0,
    "num_dockers": 0,
    "monitors": [],
    "url": "git://github.com/Todai88/CoreTesting.git",
    "langs": [
        "c#"
    ],
    "num_files": 1,
    "num_monitors": 0,
    "avg_size_service": 4199.0
}